freshroastsr700/__init__.py
freshroastsr700/exceptions.py
freshroastsr700/pid.py
freshroastsr700/utils.py
freshroastsr700/version.py
freshroastsr700-0.2.4.dist-info/DESCRIPTION.rst
freshroastsr700-0.2.4.dist-info/METADATA
freshroastsr700-0.2.4.dist-info/RECORD
freshroastsr700-0.2.4.dist-info/WHEEL
freshroastsr700-0.2.4.dist-info/metadata.json
freshroastsr700-0.2.4.dist-info/top_level.txt
