Metadata-Version: 2.0
Name: freshroastsr700
Version: 0.2.4
Summary: A Python module to control a FreshRoastSR700 coffee roaster.
Home-page: https://github.com/Roastero/freshroastsr700
Author: Mark Spicer
Author-email: mds4680@rit.edu
License: MIT
Platform: UNKNOWN
Requires-Dist: pyserial (>=3.0.1)
